sgelt/__init__.py
sgelt/__main__.py
sgelt/__version__.py
sgelt/calendar.py
sgelt/config.py
sgelt/data.py
sgelt/filters.py
sgelt/main.py
sgelt/mdparse.py
sgelt/pages.py
sgelt/py.typed
sgelt/serve.py
sgelt/sgelt.py
sgelt/utils.py
sgelt/watch.py
sgelt/theme/LICENSE
sgelt/theme/css/materialize.css
sgelt/theme/css/materialize.min.css
sgelt/theme/css/style.css
sgelt/theme/img/favicon.ico
sgelt/theme/img/iss.jpg
sgelt/theme/img/logo_jinja.png
sgelt/theme/img/logo_materialize.png
sgelt/theme/img/logo_pi.png
sgelt/theme/img/logo_python.png
sgelt/theme/js/delaunay.js
sgelt/theme/js/init.js
sgelt/theme/js/lunr-search-result.js
sgelt/theme/js/lunr.js
sgelt/theme/js/materialize.js
sgelt/theme/js/materialize.min.js
sgelt/theme/js/parallax.js
sgelt/theme/js/parallax.min.js
sgelt/theme/templates/actualites-bib.html
sgelt/theme/templates/actualites.html
sgelt/theme/templates/agenda.html
sgelt/theme/templates/article.html
sgelt/theme/templates/base.html
sgelt/theme/templates/conference.html
sgelt/theme/templates/equipe.html
sgelt/theme/templates/index.html
sgelt/theme/templates/macros.jinja.html
sgelt/theme/templates/page.html
sgelt/theme/templates/search.html
sgelt/theme/templates/seminaire.html
sgelt/theme/templates/seminaires.html
sgelt/theme/templates/soutenance.html
sgelt/theme/templates/partial/date_place.html
sgelt/theme/templates/partial/footer.html
sgelt/theme/templates/partial/nav.html
sgelt/theme/templates/partial/news_button.html
sgelt-4.9.0.dist-info/LICENSE
sgelt-4.9.0.dist-info/METADATA
sgelt-4.9.0.dist-info/WHEEL
sgelt-4.9.0.dist-info/entry_points.txt
sgelt-4.9.0.dist-info/top_level.txt
sgelt-4.9.0.dist-info/RECORD
