Metadata-Version: 2.1
Name: sgelt
Version: 4.9.0
Summary: SGELT: Site GEnerator for Labs and Teams
Author-email: Matthieu Boileau <matthieu.boileau@math.unistra.fr>
License: MIT
Project-URL: Homepage, https://gitlab.math.unistra.fr/irma/sgelt
Classifier: Programming Language :: Python :: 3
Classifier: License :: OSI Approved :: MIT License
Classifier: Operating System :: OS Independent
Requires-Python: >=3.9
License-File: LICENSE
Requires-Dist: mdslicer
Requires-Dist: datetimejson
Requires-Dist: icalendar ==4.1.0
Requires-Dist: jinja2
Requires-Dist: livereload
Requires-Dist: markdown-link-attr-modifier
Requires-Dist: shortcodes
Requires-Dist: unidecode
Requires-Dist: watchdog
Provides-Extra: tests
Requires-Dist: faker <20 ; extra == 'tests'
Requires-Dist: freezegun ; extra == 'tests'
Requires-Dist: pytest ; extra == 'tests'
Requires-Dist: pytest-cov ; extra == 'tests'
Requires-Dist: pytest-xdist[psutil] ; extra == 'tests'
Requires-Dist: pytest-mock ; extra == 'tests'
